ganalytics/__init__.py
ganalytics/client.py
ganalytics/config.py
ganalytics/domains/__init__.py
ganalytics/domains/analytics.py
ganalytics/domains/base.py
ganalytics/domains/constants.py
ganalytics/infrastructure/__init__.py
ganalytics/infrastructure/google_analytics_api.py
ganalytics/infrastructure/logger.py
ganalytics/interfaces/__init__.py
ganalytics/interfaces/ianalytics.py
ganalytics/interfaces/ilogger.py
ganalytics/interfaces/iusecases.py
ganalytics/usecases/__init__.py
ganalytics/usecases/converter.py
ganalytics/usecases/pull_reports.py
ganalytics/usecases/report_templates.py
ganalytics/utils/__init__.py
ganalytics/utils/decorators.py
ganalytics/utils/errors.py
ganalytics/utils/validators.py
ganalytics-1.0.0.dist-info/LICENSE
ganalytics-1.0.0.dist-info/METADATA
ganalytics-1.0.0.dist-info/WHEEL
ganalytics-1.0.0.dist-info/top_level.txt
ganalytics-1.0.0.dist-info/RECORD
