Metadata-Version: 2.1
Name: ganalytics
Version: 1.0.0
Summary: A python library for intuitive interaction with the Google Analytics API
Author-email: Mesake Navunawa <mesake.navunawa@gmail.com>
Project-URL: Homepage, https://github.com/Mesake94/ganalytics.git
Classifier: Programming Language :: Python :: 3
Classifier: License :: OSI Approved :: MIT License
Classifier: Operating System :: OS Independent
Requires-Python: >=3.8
License-File: LICENSE
